independent_validation/__init__.py
independent_validation/iv_file.py
independent_validation/mcmc.py
independent_validation/one_func.py
independent_validation/rv_hist_subclass.py
independent_validation/weighted_sum_distribution.py
independent_validation-0.1.3.dist-info/METADATA
independent_validation-0.1.3.dist-info/WHEEL
independent_validation-0.1.3.dist-info/licenses/LICENSE
independent_validation-0.1.3.dist-info/RECORD
